{
	"platform":"Android",
	"locales":[
	   {
		  "locale":"en",
		  "strings":{
			 "fill_up": "Fill your details or continue with \nsocial media",
			 "Welcome to":"Welcome to",
			 "button_login": "Sign In",
			 "forget_password":"Forget Password",
			 "new_user": "Don't have an account?",
			 "create_account":"SignUp",
			 "message_login":"please enter email",
			 "enter_valid_email":"Please enter a valid email",
			 "button_sign_up": "Sign Up",
			 "button_change_password": "Change Password",
			 "empty_username_password": "Please, enter password to sign in",
			 "empty_username_password_sign_up": "Please, enter password to sign up",
			 "message_login_email_password_invalid": "Invalid Email/Password",
			 "enter_email_adress_hint": "email",
			 "enter_password_hint": " password",
			 "invalid_email_address": "Invalid email address",
			 "register_account":"Register Account",
			 "enter_username":"Full Name",
			 "sign_up":"Sign Up",
			 "policy_privacy": "I have read and agree to the ",
			 "terms_of":"Terms of",
			 "use_privacy":"Use, Privacy Policy",
			 "mahmoud":"Please enter full name",
			 "confirmation_text":  "Yes, I want to receive product news",
			 "and_offers":"and offers",
			 "already_have_account":"Already have an account?",
			 "model1_text1":"UI/UX Designer",
			 "model2_text2":"Product Design",
			 "model3_text3":"Visual Design",
			 "model4_text4":"Google",
			 "model5_text5":"Lead Product Manager",
			 "model6_text6":"Toronto, Canada",
			 "model7_text7":"Shopify",
			 "model8_text8":"Senior UI Designer",
			 "drawer_text1":"Edit Profile",
			 "drawer_text2":"Applications",
			 "drawer_text3":"Settings",
			 "drawer_text4":"Share App",
			 "drawer_text5":"Logout",
			 "search_hinttext":" Search here...",
			 "home_text1":"Jobs Based On Your Interests",
			 "home_text2":"Show All",
			 "home_text3":"Recent Jobs",
			 "navbar_1":"Home",
			 "Search..":"Search"
		  }
	   },
	   {
		  "locale":"ar",
		  "strings":{
			 "fill_up": "املأ تفاصيلك أو اكمل باستخدام وسائل التواصل الاجتماعي",
			 "Welcome to": "مرحبا بعودتك",
			 "forget_password":"نسيت كلمة مرور",
			 "new_user":"مستخدم جديد؟",
			 "create_account":"انشاء حساب جديد",
			 "message_login":"ادخل بريدك الالكتروني من فضلك",
			 "enter_valid_email":"ادخل بريدالكتروني صالح الاستخدام",
			 "button_login": "تسجيل الدخول",
			 "button_sign_up": "إنشاء حساب",
			 "button_change_password": "تغيير كلمة المرور",
			 "empty_username_password": "الرجاء إدخال اسم المستخدم وكلمة المرور لتسجيل الدخول",
			 "empty_username_password_sign_up": "الرجاء أدخل كلمة المرور لإنشاء الحساب",
			 "message_login_email_password_invalid": "البريد الإلكتروني / كلمة المرور غير صحيحة",
			 "enter_email_adress_hint": "أدخل بريدك الإلكتروني",
			 "enter_password_hint": "أدخل كلمة المرور",
			 "invalid_email_address": "عنوان البريد الإلكتروني غير صحيح",
			 "register_account":"تسجيل دخول",
			 "enter_username":"اسم المستخدم",
			 "sign_up": "تسجيل دخول",
			 "policy_privacy": "لقد قرأت ووافقت ",
			 "terms_of":"على شروط ",
			 "use_privacy":"استخدام سياسة الخصوصية",
			 "mahmoud":"الرجاء ادخال الاسم كامل",
			 "confirmation_text":"نعم، أرغب بالحصول على أخبار المنتجات",
			 "and_offers":"والعروض",
			 "already_have_account":"لديك حساب سابقا؟",
			 "model1_text1":"UI/UX مصمم",
			 "model2_text2":"مصمم المنتجات",
			 "model3_text3":"مصمم مرئي",
			 "model4_text4":"غوغل",
			 "model5_text5":"مدير المنتج الرئيسي",
			 "model6_text6":"تورونتو، كندا",
			 "model7_text7":"شوبيفاي",
			 "model8_text8":"مصمم واجهة المستخدم الكبير",
			 "drawer_text1":"تعديل الملف الشخصي",
			 "drawer_text2":"تطبيقات",
			 "drawer_text3":"إعدادات",
			 "drawer_text4":"مشاركة التطبيق",
			 "drawer_text5":"تسجيل الخروج",
			 "search_hinttext":"البحث هنا...",
			 "home_text1":"وظائف شائعة",
			 "home_text2":"عرض الكل",
			 "home_text3":"مشاركات حديثة",
			 "navbar_1":"الرئيسية",
			 "Search..":"Search"
		  }
	   },
	   {
		  "locale":"fr",
		  "strings":{
			 "fill_up": "Remplissez vos coordonnées ou continuez\navec les médias sociaux",
			 "Welcome to": "Bienvenue de retour",
			 "forget_password":"Mot de passe oublié",
			 "new_user":"Nouvel utilisateur ?",
			 "create_account":"Créer un compte",
			 "message_login":"Veuillez entrer votre adresse e-mail",
			 "enter_valid_email":"Veuillez entrer une adresse e-mail valide",
			 "button_login": "Se connecter",
			 "button_sign_up": "S'inscrire",
			 "button_change_password": "Changer le mot de passe",
			 "empty_username_password": "Veuillez entrer votre nom d'utilisateur et votre mot de passe pour vous connecter",
			 "empty_username_password_sign_up": "Veuillez entrer votre mot de passe pour vous inscrire",
			 "message_login_email_password_invalid": "E-mail/Mot de passe invalide",
			 "enter_email_adress_hint": "Entrer l'adresse e-mail",
			 "enter_password_hint": "Entrer le mot de passe",
			 "invalid_email_address": "Adresse e-mail invalide",
			 "register_account":"Créer un compte",
			 "enter_username":"Nom d'utilisateur",
			 "sign_up": "S'inscrire",
			 "policy_privacy": "J'ai lu et j'accepte les ",
			 "terms_of":"Conditions ",
			 "use_privacy":"d'utilisation et la Politique de confidentialité",
			 "mahmoud":"Veuillez entrer le nom complet",
			 "confirmation_text":"Oui, je souhaite recevoir des nouvelles sur les produits",
			 "and_offers":"et des offres",
			 "already_have_account":"Vous avez déjà un compte ?",
			 "model1_text1":"Designer UI/UX",
			 "model2_text2":"Conception de produits",
			 "model3_text3":"Design visuel",
			 "model4_text4":"Google",
			 "model5_text5":"Directeur de produit principal",
			 "model6_text6":"Toronto, Canada",
			 "model7_text7":"Shopify",
			 "model8_text8":"Designer UI senior",
			 "drawer_text1":"Modifier le profil",
			 "drawer_text2":"Applications",
			 "drawer_text3":"Paramètres",
			 "drawer_text4":"Partager l'application",
			 "drawer_text5":"Déconnexion",
			 "search_hinttext":"Rechercher ici...",
			 "home_text1":"Emplois populaires",
			 "home_text2":"Tout afficher",
			 "home_text3":"Publications récentes",
			 "navbar_1":"Accueil"
		  }
	   }
	]
 }
 